libioplus/__init__.py
libioplus-1.0.0.dist-info/LICENSE
libioplus-1.0.0.dist-info/METADATA
libioplus-1.0.0.dist-info/WHEEL
libioplus-1.0.0.dist-info/top_level.txt
libioplus-1.0.0.dist-info/RECORD
